aws_hadoop/__init__.py
aws_hadoop/cluster_ops.py
aws_hadoop/config.py
aws_hadoop/hadoop_config.py
aws_hadoop/install.py
aws_hadoop/logger.py
aws_hadoop/terraform.py
aws_hadoop/templates/core-site.xml
aws_hadoop/templates/hadoop-env.sh
aws_hadoop/templates/hdfs-site.xml
aws_hadoop/templates/mapred-site.xml
aws_hadoop/templates/masters
aws_hadoop/templates/slaves
aws_hadoop/terraform/ami.tf
aws_hadoop/terraform/datanodes.tf
aws_hadoop/terraform/main.tf
aws_hadoop/terraform/master.tf
aws_hadoop/terraform/output.tf
aws_hadoop/terraform/variables.tf
aws_hadoop-1.0.dev2.dist-info/DESCRIPTION.rst
aws_hadoop-1.0.dev2.dist-info/METADATA
aws_hadoop-1.0.dev2.dist-info/RECORD
aws_hadoop-1.0.dev2.dist-info/WHEEL
aws_hadoop-1.0.dev2.dist-info/metadata.json
aws_hadoop-1.0.dev2.dist-info/top_level.txt
