Metadata-Version: 2.0
Name: aws-hadoop
Version: 1.0.dev2
Summary: Create enterprise grade Hadoop cluster in AWS in minutes.
Home-page: https://github.com/varmarakesh/aws-hadoop
Author: Rakesh Varma
Author-email: varma.rakesh@gmail.com
License: BSD
Download-URL: https://github.com/varmarakesh/aws-hadoop/tarball/1.0dev2
Platform: UNKNOWN
Classifier: Development Status :: 3 - Alpha
Classifier: Intended Audience :: Developers
Classifier: Programming Language :: Python :: 2.7
Requires-Dist: jinja2
Requires-Dist: coverage
Requires-Dist: pypi-publisher
Requires-Dist: python-terraform
Requires-Dist: fabric
Requires-Dist: pep8
